scifter_core/__init__.py
scifter_core/barcodes/__init__.py
scifter_core/barcodes/extractors.py
scifter_core/general/__init__.py
scifter_core/general/object_frame_builder.py
scifter_core/general/polars.py
scifter_core-0.1.0.dist-info/METADATA
scifter_core-0.1.0.dist-info/WHEEL
scifter_core-0.1.0.dist-info/RECORD
